simplesignals
