Metadata-Version: 1.0
Name: simplesignals
Version: 0.3.0
Summary: Unix signal handlers and worker processes, simplified
Home-page: https://github.com/j4mie/simplesignals
Author: Jamie Matthews
Author-email: jamie.matthews@gmail.com
License: Public Domain
Platform: UNKNOWN
Classifier: Programming Language :: Python
Classifier: Development Status :: 3 - Alpha
Classifier: Intended Audience :: Developers
Classifier: License :: Public Domain
Classifier: Topic :: Software Development :: Libraries :: Python Modules
Classifier: Operating System :: Unix
